comboparse/__init__.py
comboparse/comboparser.py
comboparse-1.0.1.dist-info/LICENSE
comboparse-1.0.1.dist-info/METADATA
comboparse-1.0.1.dist-info/WHEEL
comboparse-1.0.1.dist-info/top_level.txt
comboparse-1.0.1.dist-info/RECORD
