Metadata-Version: 2.1
Name: comboparse
Version: 1.0.1
Summary: Drop-in replacement for argparse with support for environment variables.
Author-email: Christopher Kaster <me@atomicptr.de>
Classifier: Intended Audience :: Developers
Classifier: License :: OSI Approved :: MIT License
Classifier: Operating System :: OS Independent
Requires-Python: >=3.10
License-File: LICENSE
